Workbook
Name _nmw1: [1]lead!$B$2
Name TABLE1: #REF!
Name TABLE2: #REF!

Sheet 21 No. P.A. Form
A1: FIRST & FINAL BILL
G2: યોજના: | H2: ૧૫ મુ નાણાપંચ ગ્રામ્ય કક્ષા વર્ષ ૨૦૨૫-૨૬ પ્રથમ હપ્તો
A3: નોંધ :- (જુઓ નિયમ - ૧૪૪)
A4: પી.એ.ફોર્મ
I5: પ્રથમ-છેવટનું બિલ
A6: પેટા વિભાગ :- ના.કા.ઇ.શ્રી, મા. અને મ. (પં.) પેટા વિભાગ, | G6: ડાકોર.
A7: કામનું નામ :- | C7: ભદ્રાસા તાબે નવાદાજીપુરામાં સી.સી. રસ્તાનું કામ. | J7: તા. ઠાસરા | Q7: 12
A8: કોન્ટ્રાક્ટર અથવા છુટક કામ કરનારનું નામ તથા સરનામું :- | G8: સરપંચ શ્રી ગ્રામ પંચાયત | J8: ભદ્રાસા | Q8: 20
E9: તાલુકા પંચાયત કચેરી | G9: =J7 -> તા. ઠાસરા | H9: ના હુકમ નંબર- | I9: જા. નં. વિકાસ/વશી/૧૭૯૧. તા. ૨૩/૦૩/૨૦૨૬. | Q9: 8
A10: માપ સામે તપાસ્યુ છે અને ખરૂ માલુમ પડયું છે. | G10: એ માપો તપાસ્યા અને જોયું અને રૂ....................... /- | Q10: 26
G11: નું બિલ મંજુર કર્યુ. | Q11: 12
A14: પે.વિ.અ.ના કારકુનની ટુંકી સહી | G14: પે.વિ.અ.ના કારકુનની ટુંકી સહી
A15: ઓવરશીયર | G15: ઓવરશીયર
A17: સહી તથા તારીખ | G17: સહી તથા તારીખ
A20: તપાસી જોયુ | G20: મુખાલસી કરી
A21: હિસાબ તપાસણી કરનાર કારકુનની ટુંકી સહી | G21: એક્ઝીક્યુટીવ એન્જીનીઅર
A22: બીલની રકમ મળી
A23: તારીખ | G23: તાલુકા /જીલ્લા/પંચાયત
A24: નાણા મેળવનારની સહી અથવા અંગુઠાની છાપ
G25: નાણાં લેનાર અભણ હોય તો
A26: રૂ....................................) આપવા | G26: સાક્ષીની સહી તથા તારીખ
A27: તારીખ...................... ..... હિસાબનીશ
A29: હિસાબનીશ | G29: મંત્રી
A30: તાલુકા/ જીલ્લા/પંચાયત | G30: તાલુકા/ જીલ્લા/પંચાયત
A31: .................................તારીખનો ચેક ક્રમાંક થી
A32: ખાતે ઉધાર્યા. | G32: પગાર કર્યા અને તે નાણાં
G34: ખાતાવહી પાનું
A35: વાઉચર ક્રમાંક

Sheet Bill
A1: ='21 No. P.A. Form'!C7 -> ભદ્રાસા તાબે નવાદાજીપુરામાં સી.સી. રસ્તાનું કામ.
A2: કામ અથવા માલની રકમ (અંદાજની પેટા સદરો પ્રમાણે સમુહમાં ગોઠવેલ) | B2: આજ તારીખ સુધીનું પરીણામ | C2: દર | D2: દીઠ | E2: આજ તારીખ સુધીની રકમ | F2: આગલા બીલથી આજ તારીખ સુધીની રકમ | G2: શેરો
A4: ITEM NO 1 : Demolition including stacking of serviceable materilas and disposal of unserviceable materials with all lead and lift. (i) R.C.C. work | B4: 0 | C4: 1030.81 | D4: Cu.m | E4: =B4*C4 -> 0
A5: Item No :- 2 Excatation for pipe line trenches incl. all safety provision using site rails & stacking excavated stuff up to a lead of 90 M. cleaing the site etc. complete for lift & strata as specified.(A) in all sorts of soil and soft murrum (a) Upto 1.5 mt. depth | B5: 205.33 | C5: 89 | D5: Cu.m | E5: =B5*C5 -> 18274.37
A6: Item No :- 3 Providing & supplying ISI standard R.C.C. pipe (or Sulphate Resistance cement) in standard length of following class & diameter suitable for either collar joints or rubber ring joints including all taxes, insurance, transportation, freight charges, octroi, inspection charges,loading, unloading, conveyance to departmental stores, stacking etc. comp. ( IS - 458 / 1989 ) for following dia.d) Class NP2 Test Pressure, 0.7 Kg/sq.cm
A7: (1) 225 mm. Dia R.C.C. Pipe | B7: 0 | C7: 421 | D7: Rmt | E7: =B7*C7 -> 0
A8: (2) 300 mm. Dia R.C.C. Pipe | B8: 100 | C8: 672 | D8: Rmt | E8: =B8*C8 -> 67200
A9: (3) 450 mm. Dia R.C.C. Pipe | B9: 92.5 | C9: 817 | D9: Rmt | E9: =B9*C9 -> 75572.5
A10: (4) 600 mm Dia R.C.C. Pipe | B10: 70 | C10: 1331 | D10: Rmt | E10: =B10*C10 -> 93170
A11: (5) 900 mm Dia. R.C.C. Pipe | B11: 0 | C11: 2476 | D11: Rmt | E11: =B11*C11 -> 0
A12: (6) 1200 mm Dia. R.C.C. Pipe | B12: 0 | C12: 4121 | D12: Rmt | E12: =B12*C12 -> 0
A13: Item No :- 4 Lowing laying & joining R.C.C. pipes in C.M. 1:1 1/2 of follwing diameter in proper position garde aligment as directed by Engg. Incl. Conveyance from store to site of work labour giving hydraulic testing as per ISI code etc. comple incl.
A14: (1) 225 mm. Dia R.C.C. Pipe | B14: =B7 -> 0 | C14: 88 | D14: Rmt | E14: =B14*C14 -> 0
A15: (2) 300 mm. Dia R.C.C. Pipe | B15: =B8 -> 100 | C15: 119 | D15: Rmt | E15: =B15*C15 -> 11900
A16: (3) 450 mm. Dia R.C.C. Pipe | B16: =B9 -> 92.5 | C16: 171 | D16: Rmt | E16: =B16*C16 -> 15817.5
A17: (4) 600 mm Dia R.C.C. Pipe | B17: =B10 -> 70 | C17: 228 | D17: Rmt | E17: =B17*C17 -> 15960
A18: (5) 900 mm Dia. R.C.C. Pipe | B18: =B11 -> 0 | C18: 340 | D18: Rmt | E18: =B18*C18 -> 0
A19: (6) 1200 mm Dia. R.C.C. Pipe | B19: =B12 -> 0 | C19: 440 | D19: Rmt | E19: =B19*C19 -> 0
A20: Item No:- 5 Constructing of valve chambers in brick or bela stone masonary, locally available in C.M. 1:6. Foundation concrete 150 mm thick in C.C. 1:4:8 of trap metal size 25 mm to 40 mm thick, inside cement plater in C.M. 1:3 and cement pointing outside in C.M. 1:3 and top cover of precast RCC slab 100 mm thick (with key hole in two parts, each with handles or MS Bar etc. comp.e as given size) Upto 1 Mt. depth from G.L. to pipe invert level incl. complete civil works but excluding cost of excavation and refilling. With cast in situ RCC slab in one single piece with fixing of CI - MH Frame and cover (excl. cost of CI -MH Frame & cover) with 23 mm thick brick masonary wall in C.M. 1:6.
A21: Chamber size: 0.60 m x 0.60 m and 1.0 mt deep | B21: 0 | C21: 5138 | D21: no. | E21: =B21*C21 -> 0
A22: Chamber size: 0.90 m x 0.90 m and 1.0 mt deep | B22: 5 | C22: 7343 | D22: no. | E22: =B22*C22 -> 36715
A23: Chamber size: 1.30 m x 0.90 m and 1.0 mt deep | B23: 2 | C23: 8882 | D23: no. | E23: =B23*C23 -> 17764
A24: Chamber size: 1.30 m x 1.30 m and 1.0 mt deep | B24: 0 | C24: 10698 | D24: no. | E24: =B24*C24 -> 0
A25: Item No :- 6 Reflling the pipeline trencher incl. ramming watering comsolidating disposial of surplus stuff as directed withing radius of 3 K.M. | B25: 154.33 | C25: 22 | D25: Cu.m | E25: =B25*C25 -> 3395.26
A26: Item No:- 7 R.C.C. precast M.H.Frame & Cover Manufacture, supply & Delivery at store or at site of work precast R.C.C. M.200 Frame & cover suitable to drainage M.H. and as per type design & Drawing including cost of reinforcement M.S.Angle or Flate, curring mold work etc. (A) Heavy Duty
A27: (1) Frame suitable for 50 cm opening of M.H. | B27: =B21+B22+B23+B24 -> 7 | C27: 1121 | D27: no. | E27: =B27*C27 -> 7847
A28: (2) Cover suitable for 50 cm opening of M.H. | B28: =B27 -> 7 | C28: 1173 | D28: no. | E28: =B28*C28 -> 8211
A29: Item No. 8 Providing and laying cement concrete 1:2:4 (1- Cement : 2- Coarse sand : 4- graded stone aggregates 20 mm nominal size) and curing complete excluding cost of formwork in (A) Foundation and Plinth | B29: 0 | C29: 3652.31 | D29: Cmt | E29: =B29*C29 -> 0
A30: Item No. 9 Providing and fixing Number plate of marble stone of requiered size set in C.M. 1:4 etc. comp. | B30: 1 | C30: 306.14 | D30: no. | E30: =B30*C30 -> 306.14
A31: Total | D31: Rs. | E31: =SUM(E4:E30) -> 372132.77
A32: ADD 18% GST | D32: Rs. | E32: =E31*18% -> 66983.899
A33: Total | D33: Rs. | E33: =E31+E32 -> 439116.67
A34: આપવાની ચોખ્ખી રકમ | D34: Rs. | E34: =ROUNDDOWN(E33,0) -> 439116
A35: શ્રી- વી.એ.ઠાકોર | B35: અ.મ.ઇ એ માપ લીધા અને નીચે જણાવેલ માપપોથી નંબર તથા પાના નંબર ઉપર તે નોંધ્યા.
A36: માપ નોંધ્યા તારીખ - | B36: 11-05-2026.
A37: MB NO - | B37: 275 | C37: PAGE NO | D37: 14 | E37: TO | F37: 15
B39: બીલ સ્વીકાર્યાના પ્રતિકરૂપે કોન્ટ્રાક્ટર અથવા છુટક કામ કરનારની સહી તથા તારીખ
A40: અ.મ.ઇ શ્રી ની સહી

Sheet COMP-14MU NAN
A1: COMPLETION CERTIFICATE
A2: GRANT | B2: :- | C2: ='21 No. P.A. Form'!H2 -> ૧૫ મુ નાણાપંચ ગ્રામ્ય કક્ષા વર્ષ ૨૦૨૫-૨૬ પ્રથમ હપ્તો
A3: NAME OF WORK | B3: :- | C3: ='21 No. P.A. Form'!C7:I7 -> ભદ્રાસા તાબે નવાદાજીપુરામાં સી.સી. રસ્તાનું કામ.
A4: DETAILS OF T.S. | B4: :- | C4: 1701,03-26.
A5: AMOUNT OF T.S. | B5: :- | C5: 379000
A6: DETAILS OF A.S. | B6: :- | C6: તાલુકા પંચાયત કચેરી ઠાસરા ના હુકમ નંબર- જા. નં. વિકાસ/વશી/૧૭૯૧. તા. ૨૩/૦૩/૨૦૨૬.
A7: AMOUNT OF A.S. | B7: :- | C7: =C5 -> 379000
A8: NAME OF AGENCY | B8: :- | C8: ='21 No. P.A. Form'!G8 -> સરપંચ શ્રી ગ્રામ પંચાયત | F8: ='21 No. P.A. Form'!J8 -> ભદ્રાસા
A9: DATE OF STARTING | B9: :- | C9: 04-05-2026.
A10: DATE OF COMPLETION | B10: :- | C10: =Bill!B36 -> 11-05-2026.
A11: ACTUAL EXPENDITURE INCURED | B11: :- | C11: =Bill!E34 -> 439116
A12: FINAL MEASUREMENT RECORDED IN | B12: :- | C12: =Bill!A37 -> MB NO - | D12: =Bill!B37 -> 275 | E12: =Bill!C37 -> PAGE NO | F12: =Bill!D37 -> 14 | G12: =Bill!E37 -> TO | H12: =Bill!F37 -> 15
A13: SHORT NOTED | B13: :- | C13: WORK IS COMPLETED.
A18: Add.Ass.Engineer
A19: TALUKA PANCHAYAT
A20: ='21 No. P.A. Form'!J7 -> તા. ઠાસરા
