Workbook
Name _nmw1: [1]lead!$B$2

Sheet FACE SHEET
A1: ESTIMATE
A3: 1. Division | D3: R & B (P) DIVISON | F3: NADIAD | G3: KHEDA | H3: JILLA PANCHAYAT.
A5: 2. Sub-Division | D5: R & B (P) SUB DIV. | F5: DAKOR | G5: NANI SINCHAI OFFICE | I5: DAKOR
D6: DEE ATVT PRANT OFFICE
A7: 3. Sanctioned Estimate No:
A9: 4. Fund Head: | D9: ધારા ફંડ વર્ષ ૨૦૨૫-૨૬.
A11: 5. Major Head:
A13: 6. Minor Head:
A15: 7. Serviceable Head:
A17: 8. Departmental Head:
A19: Estimate framed in the office of the Taluka Development Officer, Taluka Panchayat, | H19: Thasra
A20: for the expense that will be incurred in the work of…
A21: કામ નું નામ : | C21: ગોળજ ગામે ઉનાળીયા ચેરમેનના ઘર થી ખૂટતા સી.સી. રસ્તાનું કામ .
A22: Amounting to Rs. | G22: 100000
A23: Administrative approval No.:
D24: Date :
A26: & Technically sanctioned under No.:
D27: Date:
A28: Estimate prepared by | D28: MR.V.A.THAKOR. A.A.E.
A30: Estimate checked by: | D30: =D28 -> MR.V.A.THAKOR. A.A.E.
A32: Call or Authority:
A33: GENERAL DESCRIPTION
A34: SR. NO. | B34: 6 | C34: જઅમ/ધા.ફં/પ્રા.મં/૬(૧)/૨૫-૨૬/વશી/૨૧૭-૧૯/૨૫. તા. ૧૭/૦૭/૨૦૨૫.
A35: મોજે - | B35: ગોળજ | E35: મુકામે | F35: =D9 -> ધારા ફંડ વર્ષ ૨૦૨૫-૨૬.
A36: યોજના હેઠળ સુચીત સી.સી. રસ્તાના કામ માટે ગ્રાન્ટ ની ફાળવણી કરેલ છે. ગામની કુલ વસ્તી આશરે .......... છે.આ કામ ઉપરોકત યોજનમાં મંજુર થયેલ છે.આ અંદાજપત્રકમાં બોક્સ કટિંગ, બીટી મેટલ ૪૦ થી ૬૩ મીમી, મુરમ, સી સી ૧:૨:૪, રોલિંગ તકતીની આઈટમ નો સમાવેશ કરી ચાલુ વર્ષ ના માર્ગ અને મકાન ના એ.ઓં.આર ભાવ લઇ અંદાજ તૈયાર કરેલ છે.
F38: A.A.E.
F39: Taluka Panchayat | H39: =H19 -> Thasra

Sheet Abstract
A1: ABSTRACT SHEET
A2: ='FACE SHEET'!A21 -> કામ નું નામ : | B2: ='FACE SHEET'!C21 -> ગોળજ ગામે ઉનાળીયા ચેરમેનના ઘર થી ખૂટતા સી.સી. રસ્તાનું કામ .
A3: QTY. | B3: UNIT | C3: ITEM | D3: SOR RATE INCL.1% LABOUR CESS | E3: PER | F3: AMOUNT
A4: =Measurement!K4 -> 36 | B4: Cmt | C4: =Measurement!A3 -> Item No.1 :- Box cutting the road surface to proper slope and camber for making a base for road work including removing the excavated stuff and depositing on the road side slope as deirected up to 50 m. lead. | D4: 156.56 | E4: =B4 -> Cmt | F4: =A4*D5 -> 5692.32
C5: ITEM NO. 0 ITEM CODE 26008+26010A Page No:- 162,163 | D5: =TRUNC((D4*1.01),2) -> 158.12
A6: =Measurement!K9 -> 16.56 | B6: =Measurement!L9 -> Cmt | C6: =Measurement!A6 -> Item No.2 :- Supplying of crsuhed stone aggregate,chipping etc. of hard stones of following nominal size free of disintegrated pieces deletarious and organic mater | D6: =Schedule!I4 -> 677.83 | E6: =B6 -> Cmt | F6: =A6*D7 -> 11336.976 | G6: =16.56*684.6 -> 11336.976
C7: (R.A) | D7: =TRUNC((D6*1.01),2) -> 684.6
A8: =Measurement!K12 -> 4.14 | B8: Cmt | C8: =Measurement!A11 -> Item No.3 :- Supplying of crsuhed stone aggregate,chipping etc. of hard stones of following nominal size free of disintegrated pieces deletarious and organic mater | D8: =Schedule!I5 -> 171.8 | E8: =B8 -> Cmt | F8: =A8*D9 -> 718.3314
C9: (R.A) | D9: =TRUNC((D8*1.01),2) -> 173.51
A10: =Measurement!K15 -> 16.56 | B10: Cmt | C10: =Measurement!A14 -> Item No. :- 4 Spreading the stone aggregates for soiling and W. B. M. including filling the inter stices forming the surface to required camber and gradient (excluding spreading of blindage) (ii) 40 mm to 63 mm size aggreates (HB) | D10: 247.28 | E10: =B10 -> Cmt | F10: =A10*D11 -> 4135.86
C11: ITEM NO. 26.2 ITEM CODE 26018A Page No- 165 | D11: =TRUNC((D10*1.01),2) -> 249.75
A12: =Measurement!K18 -> 4.14 | B12: Cmt | C12: =Measurement!A17 -> Item No. 5 :- Spreading blindage or road crust filling the gaps in metal and levelling to gradient and camber as directed (i) Murrum | D12: 146.01 | E12: =B12 -> Cmt | F12: =A12*D13 -> 610.5258
C13: ITEM NO. 26.23 ITEM CODE 26020A Page No- 165 | D13: =TRUNC((D12*1.01),2) -> 147.47
A14: =Measurement!K24 -> 12 | B14: Cmt | C14: =Measurement!A23 -> Item No. :- 6 Providing and Laying Ordinary Ciment Concrete 1:2:4 exposed work with Curing etc. Complete including compacting with surface mechanical vibrator,mechanical loater, channaling, from work, grooving, excluding cost of reinforcement for R.C.C work . | D14: =RA!G14 -> 4866.35 | E14: =B14 -> Cmt | F14: =A14*D15 -> 58980.12
C15: AS PER RA | D15: =TRUNC((D14*1.01),2) -> 4915.01
A16: =Measurement!K27 -> 1 | B16: No | C16: Item No :- 7 Testing charges for Kapchi,Metal,Sand,Cement,C.C. Cube as per schedule of testing | D16: =RA!G28 -> 2656 | E16: =B16 -> No | F16: =A16*D16 -> 2656
C17: AS PER SCHEDULE OF TESTING
A18: =Measurement!K30 -> 1 | B18: No | C18: Item No :- 8 Providing and fixing number plate of marble stone of required size set in C. M. 1 : 4 including finishing and engraving letters etc. complete. | D18: 303.11 | E18: =B18 -> No | F18: =A18*D19 -> 306.14
C19: ITEM NO. 0 ITEM CODE 26087 Page No- 172 | D19: =TRUNC((D18*1.01),2) -> 306.14
A20: Total | F20: =SUM(F4:F19) -> 84436.273
A21: ADD 18% GST | F21: =F20*18% -> 15198.529
A22: Total | F22: =F20+F21 -> 99634.802
A23: SAY RS. | F23: ='FACE SHEET'!G22 -> 100000
A28: ADD. ASST. ENGINEER
A29: TALUKA PANCHAYAT KACHERI
A30: THASRA

Sheet Measurement
A1: ='FACE SHEET'!A21 -> કામ નું નામ : | C1: =Abstract!B2 -> ગોળજ ગામે ઉનાળીયા ચેરમેનના ઘર થી ખૂટતા સી.સી. રસ્તાનું કામ .
A2: MEASUREMENT SHEET
A3: Item No.1 :- Box cutting the road surface to proper slope and camber for making a base for road work including removing the excavated stuff and depositing on the road side slope as deirected up to 50 m. lead.
C4: 1 | D4: x | E4: 40 | F4: x | G4: 3 | H4: x | I4: 0.3 | J4: = | K4: =E4*G4*I4 -> 36 | L4: Cmt
A6: Item No.2 :- Supplying of crsuhed stone aggregate,chipping etc. of hard stones of following nominal size free of disintegrated pieces deletarious and organic mater
A7: Qty = | C7: 1 | D7: x | E7: =E4 -> 40 | F7: x | G7: =G4 -> 3 | H7: x | I7: 0.12 | J7: = | K7: =E7*G7*I7 -> 14.4
A8: Add for voids = | E8: =K7 -> 14.4 | F8: x | G8: 0.15 | K8: =E8*G8 -> 2.16
I9: Total Qty. = | K9: =SUM(K7:K8) -> 16.56 | L9: Cmt
A11: Item No.3 :- Supplying of crsuhed stone aggregate,chipping etc. of hard stones of following nominal size free of disintegrated pieces deletarious and organic mater
A12: Qty = | C12: 25 % Qty. of Item:- 2 = | G12: =K9 -> 16.56 | H12: x | I12: 25 | J12: = | K12: =I12*G12% -> 4.14 | L12: Cmt
A14: Item No. :- 4 Spreading the stone aggregates for soiling and W. B. M. including filling the inter stices forming the surface to required camber and gradient (excluding spreading of blindage) (ii) 40 mm to 63 mm size aggreates (HB)
A15: Qty same as Item No :- 2 | J15: = | K15: =K9 -> 16.56 | L15: Cmt
A17: Item No. 5 :- Spreading blindage or road crust filling the gaps in metal and levelling to gradient and camber as directed (i) Murrum
A18: Qty same as Item No :- 3 | J18: = | K18: =K12 -> 4.14 | L18: Cmt
A20: Item No. 6 :- Rolling and consolidation water bound macadam (Except laterite and kankar) including watering not excceding 150 mm thickness ( main layer including binding matenals) including filling in depressions which occurs during the process (B) With power roller excceding 8 tonne and not excecding 12 tonne.
A21: Area covered = | E21: =#REF! -> #REF! | F21: x | G21: =#REF! -> #REF! | J21: = | K21: =TRUNC((G21*E21),2) -> #REF! | L21: Smt
A23: Item No. :- 6 Providing and Laying Ordinary Ciment Concrete 1:2:4 exposed work with Curing etc. Complete including compacting with surface mechanical vibrator,mechanical loater, channaling, from work, grooving, excluding cost of reinforcement for R.C.C work .
A24: Qty = | E24: =E4 -> 40 | F24: x | G24: =G4 -> 3 | H24: x | I24: 0.1 | J24: = | K24: =E24*G24*I24 -> 12 | L24: Cmt
A26: =Abstract!C16 -> Item No :- 7 Testing charges for Kapchi,Metal,Sand,Cement,C.C. Cube as per schedule of testing
J27: = | K27: 1 | L27: No
A29: =Abstract!C18 -> Item No :- 8 Providing and fixing number plate of marble stone of required size set in C. M. 1 : 4 including finishing and engraving letters etc. complete.
J30: = | K30: 1 | L30: No

Sheet RA
A1: =Measurement!A1 -> કામ નું નામ : | C1: =Abstract!B2 -> ગોળજ ગામે ઉનાળીયા ચેરમેનના ઘર થી ખૂટતા સી.સી. રસ્તાનું કામ .
A2: RATE ANALYSIS
A3: =Measurement!A23 -> Item No. :- 6 Providing and Laying Ordinary Ciment Concrete 1:2:4 exposed work with Curing etc. Complete including compacting with surface mechanical vibrator,mechanical loater, channaling, from work, grooving, excluding cost of reinforcement for R.C.C work .
A4: S.O.R Rate of R.C.C. 1:2:4 | F4: = | G4: 3616.35 | H4: Rs./ Cmt | I4: (A)
A5: (R & B Sor P. 80 It.C. No:- 05010AA I No 5.3.13)
A6: For Vaccume dewatering System including using vaccume dewatering Machine, mechenical vibrator, mechenical flotter and mechenical trovel tor finishing
A8: Rate for this Item is Rs. 125/SQ.M for 0.10 m Th R.C.C.
A9: 1 Cum will cover 10 Sq.M Area
A10: Rate of 1 Cu.M | C10: 10 | D10: X | E10: 125 | F10: (B) | G10: =C10*E10 -> 1250 | H10: Rs./ Cmt | I10: (B)
F11: Total of A+B | G11: =SUM(G4:G10) -> 4866.35 | H11: Rs./ Cmt
A14: Rate of RCC Trimix Road in (1:2:4) | G14: =G11 -> 4866.35 | H14: Rs./ Cmt
A16: SCHEDULE OF TESTING
A17: Sr. No | B17: Item | C17: No of testing required | E17: Approved Rate | G17: Amount
A18: 1 | B18: Bricks | C18: 0 | D18: x | E18: 578 | F18: = | G18: =C18*E18 -> 0
A19: 2 | B19: Sand | C19: 1 | D19: x | E19: 388 | F19: = | G19: =C19*E19 -> 388
A20: 3 | B20: Cement | C20: 1 | D20: x | E20: 788 | F20: = | G20: =C20*E20 -> 788
A21: 4 | B21: Cube | C21: 1 | D21: x | E21: 238 | F21: = | G21: =C21*E21 -> 238
A22: 5 | B22: B.T.Kapchi | C22: 1 | D22: x | E22: 546 | F22: = | G22: =C22*E22 -> 546
A23: 6 | B23: Metal | C23: 1 | D23: x | E23: 696 | F23: = | G23: =C23*E23 -> 696
A24: 7 | B24: Paving Blocks | C24: 0 | D24: x | E24: 220 | F24: = | G24: =C24*E24 -> 0
A25: 8 | B25: Steel | C25: 0 | D25: x | E25: 294 | F25: = | G25: =C25*E25 -> 0
A26: 9 | B26: Pipe Line | C26: 0 | D26: x | E26: 300 | F26: = | G26: =C26*E26 -> 0
A27: 10 | B27: Gutter Pipe | C27: 0 | D27: x | E27: 300 | F27: = | G27: =C27*E27 -> 0
G28: =SUM(G18:G27) -> 2656
B37: A.A.E.
B38: Taluka Panchayat | D38: Thasra

Sheet Lead
A1: =Abstract!A2 -> કામ નું નામ : | B1: =Abstract!B2 -> ગોળજ ગામે ઉનાળીયા ચેરમેનના ઘર થી ખૂટતા સી.સી. રસ્તાનું કામ .
A2: LEAD CHART
A4: (A) For H.B. & B.T. Metal
A5: Sevaliya | B5: to | C5: ='FACE SHEET'!H39 -> Thasra | D5: 15 | E5: KM
A6: =C5 -> Thasra | B6: to | C6: site of work | D6: 15 | E6: KM
A7: Total | D7: =D5+D6 -> 30 | E7: KM
A8: Say | D8: =TRUNC(D7,0) -> 30 | E8: KM
A10: (B) Soft Murum
A11: Local | D11: 5 | E11: KM
A13: The Lead is Consider to be minimum and shortest motorable route
C16: PLAN
F18: W= 3.00 MT
D20: CC 10 CM THICK
D21: BT METAL 40 TO 63 MM
F23: SECTION OF ROAD
A37: A.A.E.
A38: Taluka Panchayat | B38: Thasra

Sheet Schedule
A1: =Abstract!A2 -> કામ નું નામ : | C1: =Abstract!B2 -> ગોળજ ગામે ઉનાળીયા ચેરમેનના ઘર થી ખૂટતા સી.સી. રસ્તાનું કામ .
A2: RATE ANALYSIS OF MATERIALS
A3: Sr No. | B3: Item | C3: Lead | D3: Basic Rate | E3: Upto 5.0 KM | F3: Remaining Lead | I3: Amount
A4: 2 | B4: B.T.Metal 40 to 63 mm R&B SOR 2024-25 26012A 26.50 Page 163 | C4: =Lead!D8 -> 30 | D4: 417.53 | E4: 81.8 | F4: 30 | G4: 5.95 | H4: =G4*F4 -> 178.5 | I4: =D4+E4+H4 -> 677.83
A5: 3 | B5: Soft Murum ( R&B SOR 2024-25 26016A 26.13 Page 164) | C5: =Lead!D11 -> 5 | D5: 90 | E5: 81.8 | F5: 5 | G5: 0 | H5: =TRUNC((G5*F5),2) -> 0 | I5: =D5+E5+H5 -> 171.8
E7: Above 40 mm | H7: Soft Murum
A8: For remaining lead Total lead above 5 to 10 | E8: 6.5 | H8: 5.85
A9: For remaining lead Total lead above 10 up to 15 | E9: 5.86 | H9: 5.27
A10: For remaining lead Total lead above 15 up to 25 | E10: 5.41 | H10: 4.87
A11: For remaining lead Total lead above 25 up to 50 | E11: 5.35 | H11: 4.82
A12: For remaining lead Total lead above 50 up to 100 | E12: 5.96 | H12: 5.36
B17: A.A.E.
B18: Taluka Panchayat | C18: Thasra
